cade/__init__.py
cade/cade.py
cade/cli.py
cade/metrics/__init__.py
cade/metrics/comparative.py
cade/metrics/stability.py
cade/utils/__init__.py
cade-1.2.0.dist-info/AUTHORS.rst
cade-1.2.0.dist-info/LICENSE
cade-1.2.0.dist-info/METADATA
cade-1.2.0.dist-info/WHEEL
cade-1.2.0.dist-info/top_level.txt
cade-1.2.0.dist-info/RECORD
