Metadata-Version: 2.1
Name: cade
Version: 1.2.0
Summary: Compass-aligned Distributional Embeddings
Home-page: https://github.com/vinid/cade
Author: Federico Bianchi
Author-email: f.bianchi@unibocconi.it
License: MIT license
Keywords: cade
Platform: UNKNOWN
Classifier: Development Status :: 2 - Pre-Alpha
Classifier: Intended Audience :: Developers
Classifier: License :: OSI Approved :: MIT License
Classifier: Natural Language :: English
Classifier: Programming Language :: Python :: 3.5
Classifier: Programming Language :: Python :: 3.6
Classifier: Programming Language :: Python :: 3.7
Classifier: Programming Language :: Python :: 3.8
Requires-Python: >=3.5
Requires-Dist: cython
Requires-Dist: numpy
Requires-Dist: matplotlib
Requires-Dist: smart-open (==1.10.0)
